theosGraphs/__init__.py
theosGraphs/graph.py
theosGraphs/graphHeur.py
theosGraphs/graphmaze.py
theosGraphs/maze.py
theosGraphs/mazeHeur.py
theosGraphs-0.1.dist-info/METADATA
theosGraphs-0.1.dist-info/WHEEL
theosGraphs-0.1.dist-info/top_level.txt
theosGraphs-0.1.dist-info/RECORD
