Metadata-Version: 2.1
Name: theosGraphs
Version: 0.1
Summary: A Graph package for discrete math
Home-page: http://github.com/tlincke125/Data-Structures
Author: Theo Lincke
Author-email: tlincke@protonmail.com
License: MIT
Platform: UNKNOWN
